ppt2pdf/__init__.py
ppt2pdf/main.py
ppt2pdf/utils.py
ppt2pdf/scripts/__init__.py
ppt2pdf/scripts/cli.py
ppt2pdf-0.0.3.dist-info/LICENSE
ppt2pdf-0.0.3.dist-info/METADATA
ppt2pdf-0.0.3.dist-info/WHEEL
ppt2pdf-0.0.3.dist-info/entry_points.txt
ppt2pdf-0.0.3.dist-info/top_level.txt
ppt2pdf-0.0.3.dist-info/RECORD
