Metadata-Version: 2.1
Name: ppt2pdf
Version: 0.0.3
Summary: Converts PPT to PDF
Home-page: https://github.com/Swarag-N/powerpoint-to-pdf
Author: Swarag Narayanasetty
License: UNKNOWN
Platform: UNKNOWN
Classifier: Programming Language :: Python :: 3
Classifier: License :: OSI Approved :: BSD License
Classifier: Operating System :: OS Independent
Requires-Python: >=3.6
Requires-Dist: click
Requires-Dist: comtypes
Requires-Dist: pyfiglet
Requires-Dist: PyInquirer
